orangecontrib/__init__.py
orangecontrib/gpt/.DS_Store
orangecontrib/gpt/__init__.py
orangecontrib/gpt/widgets/__init__.py
orange3_gpt-0.1.0.dist-info/LICENSE
orange3_gpt-0.1.0.dist-info/WHEEL
orange3_gpt-0.1.0.dist-info/METADATA
orange3_gpt-0.1.0.dist-info/RECORD
