Metadata-Version: 2.1
Name: orange3-gpt
Version: 0.1.0
Summary: 
License: GNU AGPL-3.0
Author: Rafael Irgolic
Author-email: hello@irgolic.com
Requires-Python: >=3.9,<4.0
Classifier: License :: Other/Proprietary License
Classifier: Programming Language :: Python :: 3
Classifier: Programming Language :: Python :: 3.9
Classifier: Programming Language :: Python :: 3.10
Classifier: Programming Language :: Python :: 3.11
Requires-Dist: openai (>=0.25.0,<0.26.0)
